[
    { "key": "Hai teman, apa kabar?" },
    { "key": "Saya baru bergabung, senang bertemu dengan kalian." },
    { "key": "Kamu pergi ke mana?" },
    { "key": "Sudah makan belum?" },
    { "key": "Saat ini saya sedang sibuk, kamu tidak merasa kesepian, kan?" },
    { "key": "Cuaca hari ini sangat bagus." },
    { "key": "Semoga harimu menyenankan." },
    { "key": "Kamu suka mendengarkan musik genre apa?" },
    { "key": "Saya sedang mencari informasi tentang Lumoz." },
    { "key": "Ada yang bisa saya bantu?" },
    { "key": "Sudah makan belum?" },
    { "key": "Apa yang biasanya kamu lakukan di akhir pekan?" },
    { "key": "Ada yang bisa membantu saya?" },
    { "key": "Sudah mencoba game ini?" },
    { "key": "Hari ini saya sangat senang." },
    { "key": "Ada cerita baru apa?" },
    { "key": "Bisa berbagi pengalaman kamu?" },
    { "key": "Saya dengar kamu sudah pergi berlibur, bagaimana?" },
    { "key": "Bagaimana dengan kamu, apa yang ingin kamu lakukan?" },
    { "key": "Kamu suka menonton film apa?" },
    { "key": "Saya sedang belajar tentang blockchain, kamu punya pengalaman, kan?" },
    { "key": "Kamu pernah mendengar tentang proyek Lumoz?" },
    { "key": "Saya ingin bergabung dengan proyek Lumoz." },
    { "key": "Apakah kamu punya informasi tentang Lumoz?" },
    { "key": "Kamu tahu cara ikut berinvestasi di Lumoz?" },
    { "key": "Saya suka makanan pedas, bagaimana dengan kamu?" },
    { "key": "Bisa bantu saya kekurangan informasi tentang proyek Lumoz?" },
    { "key": "Kamu mau melakukan apa di akhir pekan?" },
    { "key": "Cuaca hari ini benar-benar indah." },
    { "key": "Ada anggota keluarga kamu yang terkenal tidak?" },
    { "key": "Kamu sudah mencoba pekerjaan ini?" },
    { "key": "Kamu punya pekerjaan yang menarik?" },
    { "key": "Kamu suka jalan-jalan di akhir pekan?" },
    { "key": "Apakah kamu punya hobi bermain game?" },
    { "key": "Saya sudah menyelesaikan bab saya." },
    { "key": "Kamu punya hobi tidak?" },
    { "key": "Saya akan bergabung dengan proyek Lumoz." },
    { "key": "Saya rasa proyek Lumoz adalah sebuah peluang." },
    { "key": "Kamu suka pakaian untuk traveling atau tidak?" },
    { "key": "Bisa saya bantu?" },
    { "key": "Ada saran untuk saya?" },
    { "key": "Saya sering jalan-jalan di akhir pekan." },
    { "key": "Kamu membawa informasi tentang proyek Lumoz?" },
    { "key": "Sudah makan belum?" },
    { "key": "Kamu punya banyak hobi tidak?" },
    { "key": "Saya suka mendengarkan musik rock." },
    { "key": "Apa pendapat kamu tentang proyek Lumoz?" },
    { "key": "Saya akan bergabung dan berinvestasi di proyek Lumoz." },
    { "key": "Bisa berbagi pengalaman kamu tentang transaksi di Lumoz?" },
    { "key": "Saya punya pasar baru untuk Lumoz." },
    { "key": "Kamu percaya Lumoz akan berkembang pesat?" },
    { "key": "Apakah kamu ikut dalam komunitas Lumoz?" },
    { "key": "Kamu sudah berinvestasi di Lumoz?" },
    { "key": "Saya sedang mengikuti perkembangan Lumoz." },
    { "key": "Lumoz akan menjadi pilihan hebat bagi investor." },
    { "key": "Semua orang di komunitas Lumoz sangat bersemangat." },
    { "key": "Lumoz bisa mengubah cara orang bertransaksi dengan cryptocurrency." },
    { "key": "Kamu percaya Lumoz akan menjadi tren baru?" },
    { "key": "Bisa tunjukkan saya cara berinvestasi di Lumoz?" },
    { "key": "Lumoz memiliki peluang besar tahun ini." },
    { "key": "Lumoz sedang berkembang sangat cepat." },
    { "key": "Apa pendapat kamu tentang potensi Lumoz di masa depan?" },
    { "key": "Lumoz akan memberikan peluang bagi semua orang." },
    { "key": "Bisa beri saya saran tentang Lumoz?" },
    { "key": "Lumoz adalah proyek investasi yang mudah untuk diikuti." },
    { "key": "Apa pendapat kamu tentang tim pengembang Lumoz?" },
    { "key": "Sudah coba aplikasi Lumoz?" },
    { "key": "Lumoz memiliki potensi untuk menjadi salah satu cryptocurrency terbesar." },
    { "key": "Kamu tahu cara membuat dompet Lumoz?" },
    { "key": "Lumoz sedang mencari investor baru." },
    { "key": "Apa pendapat kamu tentang nilai Lumoz di masa depan?" },
    { "key": "Lumoz adalah proyek cryptocurrency yang sangat menarik." },
    { "key": "Komunitas Lumoz sangat aktif dan siap membantu." },
    { "key": "Lumoz sedang membangun komunitas yang kuat." },
    { "key": "Kamu sedang mengikuti perkembangan Lumoz?" },
    { "key": "Lumoz bisa menjadi mata uang cryptocurrency masa depan." },
    { "key": "Kamu tahu cara ikut dalam program airdrop Lumoz?" },
    { "key": "Lumoz adalah salah satu proyek yang paling menonjol di industri." },
    { "key": "Apa pendapat kamu tentang strategi pemasaran Lumoz?" },
    { "key": "Lumoz sedang menciptakan peluang bagi para investor startup." },
    { "key": "Kamu pikir Lumoz akan membantu kamu berkembang secara finansial?" },
    { "key": "Kamu sedang meneliti tentang Lumoz?" },
    { "key": "Lumoz sedang mengubah pasar cryptocurrency setiap hari." },
    { "key": "Kamu menemukan informasi tentang Lumoz di mana?" },
    { "key": "Lumoz adalah peluang yang tidak boleh dilewatkan saat ini." },
    { "key": "Kamu ikut dalam acara Lumoz?" },
    { "key": "Lumoz bisa menjadi pilihan terbaik untuk investor." },
    { "key": "Bisa berbagi pendapat kamu tentang Lumoz?" },
    { "key": "Kamu pernah mendengar tentang proyek Lumoz baru-baru ini?" },
    { "key": "Kamu percaya pada potensi Lumoz di masa depan?" },
    { "key": "Lumoz sedang membangun peluang finansial yang optimal untuk semua." },
    { "key": "Kamu ikut dalam program airdrop Lumoz?" },
    { "key": "Lumoz menarik perhatian banyak investor." },
    { "key": "Kamu pikir Lumoz akan menjadi cryptocurrency yang menonjol?" },
    { "key": "Kamu khawatir tentang kemampuan Lumoz di pasar cryptocurrency?" },
    { "key": "Lumoz sedang menciptakan revolusi di dunia cryptocurrency." }
]
